hkv4delfland/__init__.py
hkv4delfland/__main__.py
hkv4delfland/core/__init__.py
hkv4delfland/core/plausibility.py
hkv4delfland/core/waterlevelstat.py
hkv4delfland/io/__init__.py
hkv4delfland/io/bui.py
hkv4delfland/io/his.py
hkv4delfland-1.1.3.dist-info/LICENSE
hkv4delfland-1.1.3.dist-info/WHEEL
hkv4delfland-1.1.3.dist-info/METADATA
hkv4delfland-1.1.3.dist-info/RECORD
