Metadata-Version: 1.2
Name: hkv4delfland
Version: 1.1.3
Summary: package for water-statistics and plausibility checker using his- and bui-file
Home-page: https://github.com/HKV-products-services/hkv4delfland
License: UNKNOWN
Author: Mattijn van Hoek
Author-email: hoek@hkv.nl
Classifier: License :: OSI Approved :: GNU General Public License v3 or later (GPLv3+)
